dg_ai_platform/__init__.py
dg_ai_platform/dg_platform.py
dg_ai_platform/example.py
dg_ai_platform/task_process_1to1.py
dg_ai_platform/task_process_1to2.py
dg_ai_platform/task_process_1toN.py
dg_ai_platform/task_process_2to1.py
dg_ai_platform/task_process_2to2.py
dg_ai_platform/task_process_use_options.py
dg_ai_platform/test.py
dg_ai_platform/utils.py
dg_ai_platform-0.2.1.dist-info/LICENSE
dg_ai_platform-0.2.1.dist-info/METADATA
dg_ai_platform-0.2.1.dist-info/WHEEL
dg_ai_platform-0.2.1.dist-info/top_level.txt
dg_ai_platform-0.2.1.dist-info/RECORD
