Metadata-Version: 2.1
Name: dg-ai-platform
Version: 0.2.1
Summary: A AI container platform.
Home-page: https://github.com/gd4219/caldron_ai_platform
Author: Caldron Tech
Author-email: support@caldrontech.com
License: UNKNOWN
Platform: UNKNOWN
Classifier: Programming Language :: Python :: 3
Classifier: License :: OSI Approved :: MIT License
Requires-Python: >=3.6
Requires-Dist: oss2
Requires-Dist: pillow
